systemd_ctypes/__init__.py
systemd_ctypes/bus.py
systemd_ctypes/event.py
systemd_ctypes/introspection.py
systemd_ctypes/librarywrapper.py
systemd_ctypes/libsystemd.py
systemd_ctypes/signature.py
systemd_ctypes-0.dist-info/COPYING
systemd_ctypes-0.dist-info/WHEEL
systemd_ctypes-0.dist-info/METADATA
systemd_ctypes-0.dist-info/RECORD
