Metadata-Version: 2.1
Name: systemd_ctypes
Version: 0
Summary: systemd_ctypes
Author-email: Allison Karlitskaya <allison.karlitskaya@redhat.com>
Classifier: License :: OSI Approved :: GNU General Public License v3 or later (GPLv3+)
Project-URL: Home, https://github.com/allisonkarlitskaya/systemd_ctypes/
